minmaxplus/__init__.py
minmaxplus/minmax.py
minmaxplus-0.2.1.dist-info/LICENSE
minmaxplus-0.2.1.dist-info/METADATA
minmaxplus-0.2.1.dist-info/WHEEL
minmaxplus-0.2.1.dist-info/top_level.txt
minmaxplus-0.2.1.dist-info/RECORD
